Metadata-Version: 2.1
Name: scrapBoss
Version: 1.0
Summary: apikey search enggine scraping based.
Home-page: https://github.com/ExsoKamabay/Api-scrap
Author: Exso Kamabay
Author-email: <lexyong66@gmail.com>
License: Apache License 2.0
Keywords: python,free,apikey,apikey scraping based
Platform: UNKNOWN
Classifier: License :: OSI Approved :: Apache Software License
Classifier: Operating System :: OS Independent
Classifier: Programming Language :: Python :: 3
Classifier: Topic :: Utilities
